argus_htmx/.utils.py.swp
argus_htmx/__init__.py
argus_htmx/appconfig.py
argus_htmx/apps.py
argus_htmx/checks.py
argus_htmx/constants.py
argus_htmx/context_processors.py
argus_htmx/middleware.py
argus_htmx/models.py
argus_htmx/settings.py
argus_htmx/urls.py
argus_htmx/utils.py
argus_htmx/auth/__init__.py
argus_htmx/auth/views.py
argus_htmx/dateformat/__init__.py
argus_htmx/dateformat/constants.py
argus_htmx/dateformat/urls.py
argus_htmx/dateformat/views.py
argus_htmx/destinations/__init__.py
argus_htmx/destinations/urls.py
argus_htmx/incidents/__init__.py
argus_htmx/incidents/constants.py
argus_htmx/incidents/customization.py
argus_htmx/incidents/filter.py
argus_htmx/incidents/forms.py
argus_htmx/incidents/urls.py
argus_htmx/incidents/utils.py
argus_htmx/incidents/views.py
argus_htmx/management/commands/__init__.py
argus_htmx/management/commands/tailwind_config.py
argus_htmx/migrations/0001_initial.py
argus_htmx/migrations/__init__.py
argus_htmx/notificationprofiles/__init__.py
argus_htmx/notificationprofiles/urls.py
argus_htmx/static/htmx-2.0.2.min.js
argus_htmx/static/hyperscript-0.9.13.min.js
argus_htmx/static/logo_white.svg
argus_htmx/static/styles.css
argus_htmx/tailwindtheme/README.md
argus_htmx/tailwindtheme/styles.css
argus_htmx/tailwindtheme/tailwind.config.js
argus_htmx/tailwindtheme/snippets/10-tailwind.css
argus_htmx/tailwindtheme/snippets/15-alert-message.css
argus_htmx/tailwindtheme/snippets/20-loading-box.css
argus_htmx/templates/htmx_base.html
argus_htmx/templates/htmx/_base_form_modal.html
argus_htmx/templates/htmx/base.html
argus_htmx/templates/htmx/dateformat/_dateformat_dropdown.html
argus_htmx/templates/htmx/dateformat/_dateformat_list.html
argus_htmx/templates/htmx/forms/checkbox_select_multiple.html
argus_htmx/templates/htmx/forms/dropdown_select_multiple.html
argus_htmx/templates/htmx/incidents/_base.html
argus_htmx/templates/htmx/incidents/_base_incident_update_modal.html
argus_htmx/templates/htmx/incidents/_incident_ack.html
argus_htmx_frontend-0.17.dist-info/WHEEL
argus_htmx_frontend-0.17.dist-info/METADATA
argus_htmx_frontend-0.17.dist-info/RECORD
