Metadata-Version: 2.3
Name: argus-htmx-frontend
Version: 0.17
Summary: HTTP Frontend as a django app for argus-server using HTMx
Author-email: Hanne Moa <hanne.moa@sikt.no>
Requires-Python: >=3.9
Classifier: Development Status :: 2 - Pre-Alpha
Classifier: Framework :: Django
Classifier: Framework :: Django :: 4.2
Classifier: Framework :: Django :: 5.0
Classifier: Framework :: Django :: 5.1
Classifier: Programming Language :: Python :: 3 :: Only
Classifier: Environment :: Web Environment
Requires-Dist: argus-server>=1.27.0
Requires-Dist: django-htmx
Requires-Dist: django-widget-tweaks==1.5.0
Requires-Dist: social-auth-core>=4.1
Requires-Dist: social-auth-app-django>=5.0
Requires-Dist: sphinx ; extra == "docs"
Project-URL: Github, https://github.com/Uninett/argus-htmx-frontend
Provides-Extra: docs
